django_postgres_utils/__init__.py
django_postgres_utils/apps.py
django_postgres_utils/widgets.py
django_postgres_utils/static/admin/js/django_postgres_utils/hstore-widget.js
django_postgres_utils/static/admin/js/django_postgres_utils/underscore-min.js
django_postgres_utils/templates/django_postgres_utils/hstore_default_widget.html
django_postgres_utils/templates/django_postgres_utils/hstore_grappelli_widget.html
django_postgres_utils-0.1.0.dist-info/DESCRIPTION.rst
django_postgres_utils-0.1.0.dist-info/METADATA
django_postgres_utils-0.1.0.dist-info/RECORD
django_postgres_utils-0.1.0.dist-info/WHEEL
django_postgres_utils-0.1.0.dist-info/metadata.json
django_postgres_utils-0.1.0.dist-info/top_level.txt
