Metadata-Version: 2.0
Name: django-postgres-utils
Version: 0.1.0
Summary: Django Utilities for Postgresql
Home-page: https://github.com/tehamalab/django-postgres-utils
Author: Tehamalab
Author-email: developers@tehamalab.com
License: MIT
Keywords: django-postgres-utils
Platform: UNKNOWN
Classifier: Development Status :: 3 - Alpha
Classifier: Framework :: Django
Classifier: Intended Audience :: Developers
Classifier: License :: OSI Approved :: BSD License
Classifier: Natural Language :: English
Classifier: Programming Language :: Python :: 2
Classifier: Programming Language :: Python :: 2.7
Classifier: Programming Language :: Python :: 3
Classifier: Programming Language :: Python :: 3.3
Classifier: Programming Language :: Python :: 3.4
Classifier: Programming Language :: Python :: 3.5
